speech2text/__about__.py
speech2text/__init__.py
speech2text/errors.py
speech2text/transcriber/__init__.py
speech2text/transcriber/base.py
speech2text/transcriber/whisper.py
farm_haystack_speech2text-1.0.1.dist-info/METADATA
farm_haystack_speech2text-1.0.1.dist-info/WHEEL
farm_haystack_speech2text-1.0.1.dist-info/licenses/LICENSE.txt
farm_haystack_speech2text-1.0.1.dist-info/RECORD
