Metadata-Version: 2.1
Name: farm-haystack-speech2text
Version: 1.0.1
Summary: Haystack node to convert audio files into Documents.
Project-URL: Documentation, https://github.com/deepset-ai/haystack-extras/tree/main/nodes/speech2text#readme
Project-URL: Issues, https://github.com/deepset-ai/haystack-extras/issues
Project-URL: Source, https://github.com/deepset-ai/haystack-extras/tree/main/nodes/speech2text
Author-email: deepset GmbH <info@deepset.ai>
License-Expression: Apache-2.0
License-File: LICENSE.txt
Classifier: Development Status :: 4 - Beta
Classifier: Programming Language :: Python
Classifier: Programming Language :: Python :: 3.7
Classifier: Programming Language :: Python :: 3.8
Classifier: Programming Language :: Python :: 3.9
Classifier: Programming Language :: Python :: 3.10
Classifier: Programming Language :: Python :: 3.11
Classifier: Programming Language :: Python :: Implementation :: CPython
Classifier: Programming Language :: Python :: Implementation :: PyPy
Requires-Python: >=3.7
Requires-Dist: farm-haystack
Requires-Dist: numpy
Requires-Dist: openai-whisper
Requires-Dist: pydantic
Requires-Dist: torch
Requires-Dist: torchaudio
Provides-Extra: dev
Requires-Dist: pylint; extra == 'dev'
Requires-Dist: pytest; extra == 'dev'
